phone_number_validator_toolkit/__init__.py
phone_number_validator_toolkit/validator.py
phone_number_validator_toolkit-0.1.0.dist-info/METADATA
phone_number_validator_toolkit-0.1.0.dist-info/WHEEL
phone_number_validator_toolkit-0.1.0.dist-info/RECORD
