Metadata-Version: 2.1
Name: phone-number-validator-toolkit
Version: 0.1.0
Summary: A tool for validating phone numbers using NumLookupAPI
License: MIT
Author: Kirstie
Author-email: 39728053+epixieme@users.noreply.github.com
Requires-Python: >=3.12,<4.0
Classifier: License :: OSI Approved :: MIT License
Classifier: Programming Language :: Python :: 3
Classifier: Programming Language :: Python :: 3.12
Requires-Dist: requests (>=2.32.3,<3.0.0)
